MoFlow/__init__.py
MoFlow/eval.py
MoFlow/eval_dtw.py
MoFlow/moflow.py
MoFlow/moflow_.py
MoFlow/moflow_gpu.py
MoFlow/plot_cell.py
MoFlow/plot_gene.py
MoFlow/sampling.py
MoFlow/simulation.py
moflow-0.1.1.dist-info/LICENSE.txt
moflow-0.1.1.dist-info/METADATA
moflow-0.1.1.dist-info/WHEEL
moflow-0.1.1.dist-info/top_level.txt
moflow-0.1.1.dist-info/RECORD
