Metadata-Version: 2.1
Name: moflow
Version: 0.1.1
Summary: MoFlow is a deep learning framework for multi-omic RNA velocity modeling that extends the relay velocity model by incorporating chromatin accessibility.  
Author-email: Ari Hong <arih0n9@gmail.com>
License: MIT
Project-URL: Github, https://github.com/AriHong/MoFlow
Project-URL: Bug Tracker, https://github.com/AriHong/MoFlow/issues
Requires-Python: <3.8,>=3.7
License-File: LICENSE.txt
Requires-Dist: scvelo >=0.2.5
Requires-Dist: pytorch-lightning <2.0,>=1.5.2
Requires-Dist: torch <2.0,>=1.10.0
